xlsx_csv-0.1.0.dist-info/METADATA
xlsx_csv-0.1.0.dist-info/WHEEL
xlsx_csv/__init__.py
xlsx_csv/xlsx_csv.cpython-36m-x86_64-linux-gnu.so
xlsx_csv-0.1.0.dist-info/RECORD
