Metadata-Version: 2.1
Name: xlsx-csv
Version: 0.1.0
Classifier: Programming Language :: Python
Keywords: xlsx,csv
Author: Vivekanandan Muthaiyan<vivekmuthu1910@gmail.com>
Author-email: Vivekanandan Muthaiyan<vivekmuthu1910@gmail.com>
License: MIT
Project-URL: Source Code, https://github.com/vivekmuthu1910/xlsx-csv
